fastapi_caching/__init__.py
fastapi_caching/backends.py
fastapi_caching/constants.py
fastapi_caching/dependencies.py
fastapi_caching/exceptions.py
fastapi_caching/hashers.py
fastapi_caching/manager.py
fastapi_caching/objects.py
fastapi_caching/py.typed
fastapi_caching/raw.py
fastapi_caching-0.3.0.dist-info/METADATA
fastapi_caching-0.3.0.dist-info/WHEEL
fastapi_caching-0.3.0.dist-info/top_level.txt
fastapi_caching-0.3.0.dist-info/RECORD
